abstract_data_types/__init__.py
abstract_data_types/directional_graph.py
abstract_data_types/matrix.py
abstract_data_types/non_directional_graph.py
abstract_data_types-0.0.1.dist-info/LICENSE
abstract_data_types-0.0.1.dist-info/METADATA
abstract_data_types-0.0.1.dist-info/WHEEL
abstract_data_types-0.0.1.dist-info/top_level.txt
abstract_data_types-0.0.1.dist-info/RECORD
