Metadata-Version: 2.1
Name: abstract-data-types
Version: 0.0.1
Summary: Abstract data structures
Home-page: UNKNOWN
Author: Matimed (Matías Carazo Medley)
Author-email: <mcarazomedley@gmail.com>
License: UNKNOWN
Keywords: python,data,structures,graph,matrix
Platform: UNKNOWN
Classifier: Intended Audience :: Developers
Classifier: Programming Language :: Python :: 3
Classifier: Operating System :: Unix
Classifier: Operating System :: Microsoft :: Windows
License-File: LICENSE
